cleanscript/__init__.py
cleanscript/cli.py
cleanscript/gpt_commenter.py
cleanscript/optimizer.py
cleanscript/utils.py
cleanscript-1.0.1.dist-info/licenses/LICENCE.txt
cleanscript-1.0.1.dist-info/METADATA
cleanscript-1.0.1.dist-info/WHEEL
cleanscript-1.0.1.dist-info/entry_points.txt
cleanscript-1.0.1.dist-info/top_level.txt
cleanscript-1.0.1.dist-info/RECORD
